{
  "type": "FeatureCollection",
  "features": [
    {
      "type": "Feature",
      "properties": {
        "stroke": "#555555",
        "stroke-width": 2,
        "stroke-opacity": 1,
        "fill": "#555555",
        "fill-opacity": 0.5,
        "title": "American University Park"
      },
      "geometry": {
        "type": "Polygon",
        "coordinates": [
          [
            [
              -77.08565711975098,
              38.93826535658118
            ],
            [
              -77.08585560321806,
              38.938315427413905
            ],
            [
              -77.08613455295563,
              38.93833211768364
            ],
            [
              -77.08655297756195,
              38.93836967077614
            ],
            [
              -77.0878940820694,
              38.939325181661374
            ],
            [
              -77.09139168262482,
              38.94187453852668
            ],
            [
              -77.09481954574584,
              38.94436956499879
            ],
            [
              -77.09491074085236,
              38.94440294268419
            ],
            [
              -77.09671318531036,
              38.945713004422664
            ],
            [
              -77.0968097448349,
              38.945825651913154
            ],
            [
              -77.10040926933289,
              38.948474902395134
            ],
            [
              -77.10051119327545,
              38.948595889423146
            ],
            [
              -77.10054874420166,
              38.94879614336054
            ],
            [
              -77.10052192211151,
              38.948996396732234
            ],
            [
              -77.10059702396393,
              38.9491507583201
            ],
            [
              -77.09903597831726,
              38.950356435912525
            ],
            [
              -77.09591388702393,
              38.952788588155755
            ],
            [
              -77.09123075008392,
              38.956413716770115
            ],
            [
              -77.08377957344054,
              38.95114908474775
            ],
            [
              -77.08374738693237,
              38.950014342624236
            ],
            [
              -77.08375811576843,
              38.94560870103113
            ],
            [
              -77.08376884460449,
              38.944740890863685
            ],
            [
              -77.08363473415375,
              38.94471168552904
            ],
            [
              -77.08306074142456,
              38.94446552580194
            ],
            [
              -77.08280861377716,
              38.94427777628298
            ],
            [
              -77.08247601985931,
              38.94377710846823
            ],
            [
              -77.08227753639221,
              38.943522600973594
            ],
            [
              -77.08208978176117,
              38.94330981531784
            ],
            [
              -77.08207905292511,
              38.943247231179875
            ],
            [
              -77.08207368850708,
              38.94262973139052
            ],
            [
              -77.08207905292511,
              38.94243780468475
            ],
            [
              -77.08565711975098,
              38.93826535658118
            ]
          ]
        ]
      }
    }
  ]
}