{
  "type": "FeatureCollection",
  "features": [
    {
      "type": "Feature",
      "properties": {
        "stroke": "#555555",
        "stroke-width": 2,
        "stroke-opacity": 1,
        "fill": "#555555",
        "fill-opacity": 0.5,
        "title": "Stronghold"
      },
      "geometry": {
        "type": "Polygon",
        "coordinates": [
          [
            [
              -77.00904250144958,
              38.92088864300798
            ],
            [
              -77.0074599981308,
              38.920896990193825
            ],
            [
              -77.00745463371277,
              38.92122252967601
            ],
            [
              -77.00865626335144,
              38.923484570470734
            ],
            [
              -77.00644612312317,
              38.926047016644034
            ],
            [
              -77.00646758079529,
              38.92615134881066
            ],
            [
              -77.00581312179565,
              38.92623690107282
            ],
            [
              -77.00574606657027,
              38.92625776746256
            ],
            [
              -77.00570583343506,
              38.926312020047185
            ],
            [
              -77.00596332550049,
              38.926499817135124
            ],
            [
              -77.00606524944305,
              38.92667092071576
            ],
            [
              -77.0061993598938,
              38.92705068572508
            ],
            [
              -77.00635761022568,
              38.92701521325535
            ],
            [
              -77.00903445482254,
              38.926695960229516
            ],
            [
              -77.0090264081955,
              38.92578409890359
            ],
            [
              -77.00903445482254,
              38.92402085554446
            ],
            [
              -77.00904250144958,
              38.92237233986714
            ],
            [
              -77.00904250144958,
              38.92088864300798
            ]
          ]
        ]
      }
    }
  ]
}