{
  "type": "FeatureCollection",
  "features": [
    {
      "type": "Feature",
      "properties": {
        "stroke": "#555555",
        "stroke-width": 2,
        "stroke-opacity": 1,
        "fill": "#555555",
        "fill-opacity": 0.5,
        "title": "Trinidad"
      },
      "geometry": {
        "type": "Polygon",
        "coordinates": [
          [
            [
              -76.98346227407455,
              38.90013867833904
            ],
            [
              -76.98435544967651,
              38.90028062185356
            ],
            [
              -76.98525935411452,
              38.90066679027325
            ],
            [
              -76.98713153600693,
              38.90142242186221
            ],
            [
              -76.99022144079208,
              38.9027353648071
            ],
            [
              -76.99315041303635,
              38.903994013866544
            ],
            [
              -76.9857770204544,
              38.91047893817165
            ],
            [
              -76.97814613580704,
              38.91722830739041
            ],
            [
              -76.9724839925766,
              38.91732013111726
            ],
            [
              -76.97615325450897,
              38.91279141029717
            ],
            [
              -76.97619616985321,
              38.912714189970984
            ],
            [
              -76.97624444961548,
              38.91261609916528
            ],
            [
              -76.97691768407822,
              38.91057077063118
            ],
            [
              -76.97720736265182,
              38.90963156941604
            ],
            [
              -76.97734415531158,
              38.90936024230698
            ],
            [
              -76.97786450386047,
              38.90851494735717
            ],
            [
              -76.97816491127014,
              38.90802446295665
            ],
            [
              -76.97866648435593,
              38.90738161018511
            ],
            [
              -76.97941213846207,
              38.90625242937306
            ],
            [
              -76.98041260242462,
              38.904693253702575
            ],
            [
              -76.98327720165253,
              38.9002555730187
            ],
            [
              -76.9833442568779,
              38.90018668867718
            ],
            [
              -76.98346227407455,
              38.90013867833904
            ]
          ]
        ]
      }
    }
  ]
}