{
  "type": "FeatureCollection",
  "features": [
    {
      "type": "Feature",
      "properties": {
        "fillColor": "#F44336",
        "title": "Lutz"
      },
      "geometry": {
        "type": "Polygon",
        "coordinates": [
          [
            [
              -82.49305486679076,
              28.172639442815456
            ],
            [
              -82.5021743774414,
              28.17267727392965
            ],
            [
              -82.50226020812987,
              28.169102174534455
            ],
            [
              -82.5021743774414,
              28.168250942784656
            ],
            [
              -82.49944925308228,
              28.163351499506366
            ],
            [
              -82.49831199645995,
              28.16270831269
            ],
            [
              -82.49668121337889,
              28.16217862652705
            ],
            [
              -82.49571561813353,
              28.161232751858613
            ],
            [
              -82.4952220916748,
              28.160343622048366
            ],
            [
              -82.4944281578064,
              28.158811274616607
            ],
            [
              -82.49290466308594,
              28.155405979563977
            ],
            [
              -82.49159574508667,
              28.155178956042292
            ],
            [
              -82.48992204666138,
              28.155065444100934
            ],
            [
              -82.48876333236694,
              28.15527354923484
            ],
            [
              -82.48751878738403,
              28.15591678072754
            ],
            [
              -82.4868321418762,
              28.15650325313192
            ],
            [
              -82.48623132705688,
              28.15725998697073
            ],
            [
              -82.48552322387694,
              28.15771402470629
            ],
            [
              -82.48481512069702,
              28.157978879162716
            ],
            [
              -82.48307704925537,
              28.15790320652775
            ],
            [
              -82.48526573181152,
              28.156276231937152
            ],
            [
              -82.48942852020264,
              28.15319247969223
            ],
            [
              -82.4914240837097,
              28.1516411106256
            ],
            [
              -82.49234676361084,
              28.15073298171754
            ],
            [
              -82.49322652816772,
              28.149711327489737
            ],
            [
              -82.49618768692017,
              28.145416489217855
            ],
            [
              -82.49895572662354,
              28.140989030717414
            ],
            [
              -82.50056505203247,
              28.138377879661427
            ],
            [
              -82.5011658668518,
              28.13678845220628
            ],
            [
              -82.5018310546875,
              28.13425288817048
            ],
            [
              -82.50213146209717,
              28.132909393355284
            ],
            [
              -82.50243186950684,
              28.1279704859558
            ],
            [
              -82.50251770019531,
              28.118981468943755
            ],
            [
              -82.50081181526183,
              28.118631355136934
            ],
            [
              -82.50033974647522,
              28.118555654704043
            ],
            [
              -82.4998140335083,
              28.118678667880346
            ],
            [
              -82.498859167099,
              28.119218031679566
            ],
            [
              -82.49753952026367,
              28.11758100685703
            ],
            [
              -82.49650955200195,
              28.11684291812666
            ],
            [
              -82.49480366706848,
              28.116653663787694
            ],
            [
              -82.49343037605286,
              28.11677667914601
            ],
            [
              -82.49198198318481,
              28.11722142580252
            ],
            [
              -82.491295337677,
              28.117997362361052
            ],
            [
              -82.49049067497253,
              28.119208569180138
            ],
            [
              -82.49072670936584,
              28.120713096096544
            ],
            [
              -82.49067306518555,
              28.12088341856803
            ],
            [
              -82.48567342758179,
              28.119956104060584
            ],
            [
              -82.48531937599182,
              28.119870942122077
            ],
            [
              -82.48498678207397,
              28.11969115558531
            ],
            [
              -82.48478293418884,
              28.119473518847965
            ],
            [
              -82.4845039844513,
              28.119265344164084
            ],
            [
              -82.48426795005798,
              28.119161256670555
            ],
            [
              -82.48167157173157,
              28.119170719174132
            ],
            [
              -82.48078107833862,
              28.118858456114868
            ],
            [
              -82.4805235862732,
              28.118858456114868
            ],
            [
              -82.48024463653563,
              28.11876383076587
            ],
            [
              -82.47970819473267,
              28.11870705551636
            ],
            [
              -82.47479438781738,
              28.118716518060037
            ],
            [
              -82.4744188785553,
              28.118631355136934
            ],
            [
              -82.47417211532593,
              28.118470491653184
            ],
            [
              -82.47395753860474,
              28.117921661480572
            ],
            [
              -82.47385025024414,
              28.117770259559286
            ],
            [
              -82.47366786003113,
              28.117789184811134
            ],
            [
              -82.47348546981812,
              28.11774187167524
            ],
            [
              -82.47203707695007,
              28.117722946415043
            ],
            [
              -82.46734857559204,
              28.11770402115149
            ],
            [
              -82.46732711791992,
              28.117467455075356
            ],
            [
              -82.46717691421509,
              28.117249813824348
            ],
            [
              -82.4670910835266,
              28.1171551870557
            ],
            [
              -82.4668550491333,
              28.117032172131594
            ],
            [
              -82.466801404953,
              28.11693754517087
            ],
            [
              -82.4662435054779,
              28.116890231659212
            ],
            [
              -82.46482729911804,
              28.116852380834835
            ],
            [
              -82.46205925941467,
              28.116795604573223
            ],
            [
              -82.4617052078247,
              28.116729365563362
            ],
            [
              -82.46153354644775,
              28.11642655813999
            ],
            [
              -82.4610185623169,
              28.11214931194703
            ],
            [
              -82.4603533744812,
              28.108515411247108
            ],
            [
              -82.4603533744812,
              28.107058031066973
            ],
            [
              -82.46050357818602,
              28.10367001881078
            ],
            [
              -82.46056795120239,
              28.10134188133032
            ],
            [
              -82.46078252792358,
              28.1003386845662
            ],
            [
              -82.46119022369383,
              28.098729764512647
            ],
            [
              -82.45507478713989,
              28.098483692259954
            ],
            [
              -82.45452761650085,
              28.098635121405312
            ],
            [
              -82.45392680168152,
              28.098786550336964
            ],
            [
              -82.45325088500977,
              28.098824407536494
            ],
            [
              -82.4531328678131,
              28.098833871834284
            ],
            [
              -82.45298266410828,
              28.098578335500843
            ],
            [
              -82.45269298553467,
              28.09808618973675
            ],
            [
              -82.45240330696106,
              28.097480468774847
            ],
            [
              -82.45200634002686,
              28.09662866788789
            ],
            [
              -82.451491355896,
              28.09445181268368
            ],
            [
              -82.45146989822388,
              28.093429621962866
            ],
            [
              -82.451491355896,
              28.091442001027456
            ],
            [
              -82.44998931884764,
              28.09146093092424
            ],
            [
              -82.44962453842163,
              28.091347351493447
            ],
            [
              -82.4492597579956,
              28.09117698212193
            ],
            [
              -82.44898080825806,
              28.09108233235426
            ],
            [
              -82.44874477386475,
              28.09108233235426
            ],
            [
              -82.44844436645508,
              28.091214842005645
            ],
            [
              -82.44812250137329,
              28.09138521131706
            ],
            [
              -82.44767189025877,
              28.09147986081769
            ],
            [
              -82.44707107543945,
              28.091517720594563
            ],
            [
              -82.44612693786621,
              28.091517720594563
            ],
            [
              -82.4420714378357,
              28.091536650478012
            ],
            [
              -82.43089199066162,
              28.091669159568575
            ],
            [
              -82.43065595626831,
              28.091650229708506
            ],
            [
              -82.43061304092407,
              28.096382590817424
            ],
            [
              -82.43063449859619,
              28.10724730233896
            ],
            [
              -82.42825269699097,
              28.108439703673366
            ],
            [
              -82.42623567581177,
              28.109783505163875
            ],
            [
              -82.42511987686157,
              28.110786613612213
            ],
            [
              -82.42434740066527,
              28.112035754413768
            ],
            [
              -82.42243766784668,
              28.115972345401683
            ],
            [
              -82.41760969161987,
              28.125642875977558
            ],
            [
              -82.41273880004883,
              28.135312534170257
            ],
            [
              -82.40977764129639,
              28.14284328774692
            ],
            [
              -82.40638732910156,
              28.151830303178656
            ],
            [
              -82.40563631057739,
              28.153835723688353
            ],
            [
              -82.40411281585693,
              28.15690053906431
            ],
            [
              -82.40344762802124,
              28.157865370190216
            ],
            [
              -82.40140914916992,
              28.160835482005172
            ],
            [
              -82.39915609359741,
              28.16461894456578
            ],
            [
              -82.39434957504272,
              28.17114510310318
            ],
            [
              -82.40331888198853,
              28.17114510310318
            ],
            [
              -82.40314722061157,
              28.18315597742034
            ],
            [
              -82.40312576293945,
              28.18589842884423
            ],
            [
              -82.40316867828369,
              28.186049734461527
            ],
            [
              -82.40323305130005,
              28.18616321353399
            ],
            [
              -82.40404844284058,
              28.185860602406464
            ],
            [
              -82.40467071533203,
              28.185728209768833
            ],
            [
              -82.40525007247923,
              28.18565255675944
            ],
            [
              -82.40638732910156,
              28.18559581696729
            ],
            [
              -82.4072241783142,
              28.185614730234683
            ],
            [
              -82.42926120758055,
              28.18578494949076
            ],
            [
              -82.44565486907959,
              28.18565255675944
            ],
            [
              -82.44973182678223,
              28.18563364349874
            ],
            [
              -82.45056867599487,
              28.185709296521516
            ],
            [
              -82.45134115219116,
              28.18591734205811
            ],
            [
              -82.45346546173096,
              28.186881911529273
            ],
            [
              -82.45842218399048,
              28.189170365066918
            ],
            [
              -82.46194124221802,
              28.190626628176478
            ],
            [
              -82.46365785598755,
              28.191042699706916
            ],
            [
              -82.46657609939575,
              28.19168571615944
            ],
            [
              -82.46762752532959,
              28.192101783567573
            ],
            [
              -82.46930122375488,
              28.192858265614998
            ],
            [
              -82.47164011001587,
              28.193482359273705
            ],
            [
              -82.47344255447388,
              28.193501271145877
            ],
            [
              -82.47496604919432,
              28.193274328459033
            ],
            [
              -82.47644662857056,
              28.19299064942285
            ],
            [
              -82.47827053070067,
              28.192763705651867
            ],
            [
              -82.4802017211914,
              28.193047385290324
            ],
            [
              -82.48279809951782,
              28.194144272808543
            ],
            [
              -82.48520135879517,
              28.19569502560955
            ],
            [
              -82.48541593551636,
              28.195846317361077
            ],
            [
              -82.48560905456543,
              28.186390171317576
            ],
            [
              -82.48560905456543,
              28.1862861490599
            ],
            [
              -82.48688578605652,
              28.186182126701027
            ],
            [
              -82.48803377151489,
              28.184508298464895
            ],
            [
              -82.48911738395691,
              28.181964407641065
            ],
            [
              -82.49087691307068,
              28.18169961255364
            ],
            [
              -82.49112367630005,
              28.181075450110473
            ],
            [
              -82.49236822128296,
              28.177595204856864
            ],
            [
              -82.49260425567627,
              28.176668381319253
            ],
            [
              -82.49305486679076,
              28.172639442815456
            ]
          ]
        ]
      }
    }
  ]
}